{"nodes": [{"id": "d_projects_depi_projects_grand_project_backend_nlp_py", "label": "nlp.py", "file_type": "code", "source_file": "backend/nlp.py", "source_location": "L1"}, {"id": "d_projects_depi_projects_grand_project_backend_nlp_load_arabert", "label": "_load_arabert()", "file_type": "code", "source_file": "backend/nlp.py", "source_location": "L57", "_callable": true}, {"id": "d_projects_depi_projects_grand_project_backend_nlp_sentencebuffer", "label": "SentenceBuffer", "file_type": "code", "source_file": "backend/nlp.py", "source_location": "L78", "_callable": true}, {"id": "d_projects_depi_projects_grand_project_backend_nlp_sentencebuffer_init", "label": ".__init__()", "file_type": "code", "source_file": "backend/nlp.py", "source_location": "L91", "_callable": true}, {"id": "d_projects_depi_projects_grand_project_backend_nlp_sentencebuffer_push", "label": ".push()", "file_type": "code", "source_file": "backend/nlp.py", "source_location": "L96", "_callable": true}, {"id": "d_projects_depi_projects_grand_project_backend_nlp_sentencebuffer_flush", "label": ".flush()", "file_type": "code", "source_file": "backend/nlp.py", "source_location": "L132", "_callable": true}, {"id": "d_projects_depi_projects_grand_project_backend_nlp_sentencebuffer_pending_words", "label": ".pending_words()", "file_type": "code", "source_file": "backend/nlp.py", "source_location": "L145", "_callable": true}, {"id": "d_projects_depi_projects_grand_project_backend_nlp_sentencebuffer_preview", "label": ".preview()", "file_type": "code", "source_file": "backend/nlp.py", "source_location": "L149", "_callable": true}, {"id": "d_projects_depi_projects_grand_project_backend_nlp_correct_sentence", "label": "correct_sentence()", "file_type": "code", "source_file": "backend/nlp.py", "source_location": "L158", "_callable": true}, {"id": "d_projects_depi_projects_grand_project_backend_nlp_apply_token_corrections", "label": "_apply_token_corrections()", "file_type": "code", "source_file": "backend/nlp.py", "source_location": "L178", "_callable": true}, {"id": "d_projects_depi_projects_grand_project_backend_nlp_remove_consecutive_duplicates", "label": "_remove_consecutive_duplicates()", "file_type": "code", "source_file": "backend/nlp.py", "source_location": "L183", "_callable": true}, {"id": "d_projects_depi_projects_grand_project_backend_nlp_normalise_whitespace", "label": "_normalise_whitespace()", "file_type": "code", "source_file": "backend/nlp.py", "source_location": "L194", "_callable": true}, {"id": "d_projects_depi_projects_grand_project_backend_nlp_add_punctuation", "label": "_add_punctuation()", "file_type": "code", "source_file": "backend/nlp.py", "source_location": "L198", "_callable": true}, {"id": "d_projects_depi_projects_grand_project_backend_nlp_arabert_correct", "label": "_arabert_correct()", "file_type": "code", "source_file": "backend/nlp.py", "source_location": "L204", "_callable": true}, {"id": "d_projects_depi_projects_grand_project_backend_nlp_format_for_subtitle", "label": "format_for_subtitle()", "file_type": "code", "source_file": "backend/nlp.py", "source_location": "L225", "_callable": true}, {"id": "d_projects_depi_projects_grand_project_backend_nlp_rationale_1", "label": "backend/nlp.py ============== Arabic NLP post-processing pipeline.  Responsibili", "file_type": "rationale", "source_file": "backend/nlp.py", "source_location": "L1"}, {"id": "d_projects_depi_projects_grand_project_backend_nlp_rationale_79", "label": "Accumulates committed sign labels and produces corrected Arabic sentences.", "file_type": "rationale", "source_file": "backend/nlp.py", "source_location": "L79"}, {"id": "d_projects_depi_projects_grand_project_backend_nlp_rationale_97", "label": "Add a committed sign token to the buffer.          Returns a completed sentence", "file_type": "rationale", "source_file": "backend/nlp.py", "source_location": "L97"}, {"id": "d_projects_depi_projects_grand_project_backend_nlp_rationale_133", "label": "Finalise, correct, and return the current sentence then clear buffer.", "file_type": "rationale", "source_file": "backend/nlp.py", "source_location": "L133"}, {"id": "d_projects_depi_projects_grand_project_backend_nlp_rationale_150", "label": "Live preview of the buffer (uncorrected).", "file_type": "rationale", "source_file": "backend/nlp.py", "source_location": "L150"}, {"id": "d_projects_depi_projects_grand_project_backend_nlp_rationale_159", "label": "Full correction pipeline:       1. Token-level corrections.       2. Remove cons", "file_type": "rationale", "source_file": "backend/nlp.py", "source_location": "L159"}, {"id": "d_projects_depi_projects_grand_project_backend_nlp_rationale_205", "label": "Optionally run an AraBERT fill-mask pass for grammar refinement.", "file_type": "rationale", "source_file": "backend/nlp.py", "source_location": "L205"}, {"id": "d_projects_depi_projects_grand_project_backend_nlp_rationale_226", "label": "Return a dict suitable for JSON serialisation to the Chrome Extension.", "file_type": "rationale", "source_file": "backend/nlp.py", "source_location": "L226"}], "edges": [{"source": "d_projects_depi_projects_grand_project_backend_nlp_py", "target": "logging", "relation": "imports", "context": "import", "confidence": "EXTRACTED", "source_file": "backend/nlp.py", "source_location": "L17", "weight": 1.0}, {"source": "d_projects_depi_projects_grand_project_backend_nlp_py", "target": "re", "relation": "imports", "context": "import", "confidence": "EXTRACTED", "source_file": "backend/nlp.py", "source_location": "L18", "weight": 1.0}, {"source": "d_projects_depi_projects_grand_project_backend_nlp_py", "target": "time", "relation": "imports", "context": "import", "confidence": "EXTRACTED", "source_file": "backend/nlp.py", "source_location": "L19", "weight": 1.0}, {"source": "d_projects_depi_projects_grand_project_backend_nlp_py", "target": "typing", "relation": "imports_from", "context": "import", "confidence": "EXTRACTED", "source_file": "backend/nlp.py", "source_location": "L20", "weight": 1.0}, {"source": "d_projects_depi_projects_grand_project_backend_nlp_py", "target": "d_projects_depi_projects_grand_project_backend_init_py", "relation": "imports_from", "context": "import", "confidence": "EXTRACTED", "source_file": "backend/nlp.py", "source_location": "L22", "weight": 1.0}, {"source": "d_projects_depi_projects_grand_project_backend_nlp_py", "target": "d_projects_depi_projects_grand_project_backend_nlp_load_arabert", "relation": "contains", "confidence": "EXTRACTED", "source_file": "backend/nlp.py", "source_location": "L57", "weight": 1.0}, {"source": "d_projects_depi_projects_grand_project_backend_nlp_py", "target": "d_projects_depi_projects_grand_project_backend_nlp_sentencebuffer", "relation": "contains", "confidence": "EXTRACTED", "source_file": "backend/nlp.py", "source_location": "L78", "weight": 1.0}, {"source": "d_projects_depi_projects_grand_project_backend_nlp_sentencebuffer", "target": "d_projects_depi_projects_grand_project_backend_nlp_sentencebuffer_init", "relation": "method", "confidence": "EXTRACTED", "source_file": "backend/nlp.py", "source_location": "L91", "weight": 1.0}, {"source": "d_projects_depi_projects_grand_project_backend_nlp_sentencebuffer", "target": "d_projects_depi_projects_grand_project_backend_nlp_sentencebuffer_push", "relation": "method", "confidence": "EXTRACTED", "source_file": "backend/nlp.py", "source_location": "L96", "weight": 1.0}, {"source": "d_projects_depi_projects_grand_project_backend_nlp_sentencebuffer", "target": "d_projects_depi_projects_grand_project_backend_nlp_sentencebuffer_flush", "relation": "method", "confidence": "EXTRACTED", "source_file": "backend/nlp.py", "source_location": "L132", "weight": 1.0}, {"source": "d_projects_depi_projects_grand_project_backend_nlp_sentencebuffer", "target": "d_projects_depi_projects_grand_project_backend_nlp_sentencebuffer_pending_words", "relation": "method", "confidence": "EXTRACTED", "source_file": "backend/nlp.py", "source_location": "L145", "weight": 1.0}, {"source": "d_projects_depi_projects_grand_project_backend_nlp_sentencebuffer", "target": "d_projects_depi_projects_grand_project_backend_nlp_sentencebuffer_preview", "relation": "method", "confidence": "EXTRACTED", "source_file": "backend/nlp.py", "source_location": "L149", "weight": 1.0}, {"source": "d_projects_depi_projects_grand_project_backend_nlp_py", "target": "d_projects_depi_projects_grand_project_backend_nlp_correct_sentence", "relation": "contains", "confidence": "EXTRACTED", "source_file": "backend/nlp.py", "source_location": "L158", "weight": 1.0}, {"source": "d_projects_depi_projects_grand_project_backend_nlp_py", "target": "d_projects_depi_projects_grand_project_backend_nlp_apply_token_corrections", "relation": "contains", "confidence": "EXTRACTED", "source_file": "backend/nlp.py", "source_location": "L178", "weight": 1.0}, {"source": "d_projects_depi_projects_grand_project_backend_nlp_py", "target": "d_projects_depi_projects_grand_project_backend_nlp_remove_consecutive_duplicates", "relation": "contains", "confidence": "EXTRACTED", "source_file": "backend/nlp.py", "source_location": "L183", "weight": 1.0}, {"source": "d_projects_depi_projects_grand_project_backend_nlp_py", "target": "d_projects_depi_projects_grand_project_backend_nlp_normalise_whitespace", "relation": "contains", "confidence": "EXTRACTED", "source_file": "backend/nlp.py", "source_location": "L194", "weight": 1.0}, {"source": "d_projects_depi_projects_grand_project_backend_nlp_py", "target": "d_projects_depi_projects_grand_project_backend_nlp_add_punctuation", "relation": "contains", "confidence": "EXTRACTED", "source_file": "backend/nlp.py", "source_location": "L198", "weight": 1.0}, {"source": "d_projects_depi_projects_grand_project_backend_nlp_py", "target": "d_projects_depi_projects_grand_project_backend_nlp_arabert_correct", "relation": "contains", "confidence": "EXTRACTED", "source_file": "backend/nlp.py", "source_location": "L204", "weight": 1.0}, {"source": "d_projects_depi_projects_grand_project_backend_nlp_py", "target": "d_projects_depi_projects_grand_project_backend_nlp_format_for_subtitle", "relation": "contains", "confidence": "EXTRACTED", "source_file": "backend/nlp.py", "source_location": "L225", "weight": 1.0}, {"source": "d_projects_depi_projects_grand_project_backend_nlp_sentencebuffer_push", "target": "d_projects_depi_projects_grand_project_backend_nlp_sentencebuffer_flush", "relation": "calls", "context": "call", "confidence": "EXTRACTED", "source_file": "backend/nlp.py", "source_location": "L108", "weight": 1.0}, {"source": "d_projects_depi_projects_grand_project_backend_nlp_sentencebuffer_flush", "target": "d_projects_depi_projects_grand_project_backend_nlp_correct_sentence", "relation": "calls", "context": "call", "confidence": "EXTRACTED", "source_file": "backend/nlp.py", "source_location": "L139", "weight": 1.0}, {"source": "d_projects_depi_projects_grand_project_backend_nlp_correct_sentence", "target": "d_projects_depi_projects_grand_project_backend_nlp_apply_token_corrections", "relation": "calls", "context": "call", "confidence": "EXTRACTED", "source_file": "backend/nlp.py", "source_location": "L167", "weight": 1.0}, {"source": "d_projects_depi_projects_grand_project_backend_nlp_correct_sentence", "target": "d_projects_depi_projects_grand_project_backend_nlp_remove_consecutive_duplicates", "relation": "calls", "context": "call", "confidence": "EXTRACTED", "source_file": "backend/nlp.py", "source_location": "L168", "weight": 1.0}, {"source": "d_projects_depi_projects_grand_project_backend_nlp_correct_sentence", "target": "d_projects_depi_projects_grand_project_backend_nlp_normalise_whitespace", "relation": "calls", "context": "call", "confidence": "EXTRACTED", "source_file": "backend/nlp.py", "source_location": "L169", "weight": 1.0}, {"source": "d_projects_depi_projects_grand_project_backend_nlp_correct_sentence", "target": "d_projects_depi_projects_grand_project_backend_nlp_add_punctuation", "relation": "calls", "context": "call", "confidence": "EXTRACTED", "source_file": "backend/nlp.py", "source_location": "L170", "weight": 1.0}, {"source": "d_projects_depi_projects_grand_project_backend_nlp_correct_sentence", "target": "d_projects_depi_projects_grand_project_backend_nlp_arabert_correct", "relation": "calls", "context": "call", "confidence": "EXTRACTED", "source_file": "backend/nlp.py", "source_location": "L173", "weight": 1.0}, {"source": "d_projects_depi_projects_grand_project_backend_nlp_arabert_correct", "target": "d_projects_depi_projects_grand_project_backend_nlp_load_arabert", "relation": "calls", "context": "call", "confidence": "EXTRACTED", "source_file": "backend/nlp.py", "source_location": "L208", "weight": 1.0}, {"source": "d_projects_depi_projects_grand_project_backend_nlp_rationale_1", "target": "d_projects_depi_projects_grand_project_backend_nlp_py", "relation": "rationale_for", "confidence": "EXTRACTED", "source_file": "backend/nlp.py", "source_location": "L1", "weight": 1.0}, {"source": "d_projects_depi_projects_grand_project_backend_nlp_rationale_79", "target": "d_projects_depi_projects_grand_project_backend_nlp_sentencebuffer", "relation": "rationale_for", "confidence": "EXTRACTED", "source_file": "backend/nlp.py", "source_location": "L79", "weight": 1.0}, {"source": "d_projects_depi_projects_grand_project_backend_nlp_rationale_97", "target": "d_projects_depi_projects_grand_project_backend_nlp_sentencebuffer_push", "relation": "rationale_for", "confidence": "EXTRACTED", "source_file": "backend/nlp.py", "source_location": "L97", "weight": 1.0}, {"source": "d_projects_depi_projects_grand_project_backend_nlp_rationale_133", "target": "d_projects_depi_projects_grand_project_backend_nlp_sentencebuffer_flush", "relation": "rationale_for", "confidence": "EXTRACTED", "source_file": "backend/nlp.py", "source_location": "L133", "weight": 1.0}, {"source": "d_projects_depi_projects_grand_project_backend_nlp_rationale_150", "target": "d_projects_depi_projects_grand_project_backend_nlp_sentencebuffer_preview", "relation": "rationale_for", "confidence": "EXTRACTED", "source_file": "backend/nlp.py", "source_location": "L150", "weight": 1.0}, {"source": "d_projects_depi_projects_grand_project_backend_nlp_rationale_159", "target": "d_projects_depi_projects_grand_project_backend_nlp_correct_sentence", "relation": "rationale_for", "confidence": "EXTRACTED", "source_file": "backend/nlp.py", "source_location": "L159", "weight": 1.0}, {"source": "d_projects_depi_projects_grand_project_backend_nlp_rationale_205", "target": "d_projects_depi_projects_grand_project_backend_nlp_arabert_correct", "relation": "rationale_for", "confidence": "EXTRACTED", "source_file": "backend/nlp.py", "source_location": "L205", "weight": 1.0}, {"source": "d_projects_depi_projects_grand_project_backend_nlp_rationale_226", "target": "d_projects_depi_projects_grand_project_backend_nlp_format_for_subtitle", "relation": "rationale_for", "confidence": "EXTRACTED", "source_file": "backend/nlp.py", "source_location": "L226", "weight": 1.0}], "raw_calls": [{"caller_nid": "d_projects_depi_projects_grand_project_backend_nlp_load_arabert", "callee": "hf_pipeline", "is_member_call": false, "source_file": "backend/nlp.py", "source_location": "L63", "receiver": null}, {"caller_nid": "d_projects_depi_projects_grand_project_backend_nlp_load_arabert", "callee": "info", "is_member_call": true, "source_file": "backend/nlp.py", "source_location": "L68", "receiver": "logger"}, {"caller_nid": "d_projects_depi_projects_grand_project_backend_nlp_load_arabert", "callee": "warning", "is_member_call": true, "source_file": "backend/nlp.py", "source_location": "L70", "receiver": "logger"}, {"caller_nid": "d_projects_depi_projects_grand_project_backend_nlp_load_arabert", "callee": "exc", "is_member_call": false, "indirect": true, "context": "argument", "source_file": "backend/nlp.py", "source_location": "L70"}, {"caller_nid": "d_projects_depi_projects_grand_project_backend_nlp_sentencebuffer_push", "callee": "monotonic", "is_member_call": true, "source_file": "backend/nlp.py", "source_location": "L103", "receiver": "time"}, {"caller_nid": "d_projects_depi_projects_grand_project_backend_nlp_sentencebuffer_push", "callee": "strip", "is_member_call": true, "source_file": "backend/nlp.py", "source_location": "L114", "receiver": "token"}, {"caller_nid": "d_projects_depi_projects_grand_project_backend_nlp_sentencebuffer_push", "callee": "lower", "is_member_call": true, "source_file": "backend/nlp.py", "source_location": "L115", "receiver": "token"}, {"caller_nid": "d_projects_depi_projects_grand_project_backend_nlp_sentencebuffer_push", "callee": "append", "is_member_call": true, "source_file": "backend/nlp.py", "source_location": "L122", "receiver": null}, {"caller_nid": "d_projects_depi_projects_grand_project_backend_nlp_sentencebuffer_flush", "callee": "join", "is_member_call": true, "source_file": "backend/nlp.py", "source_location": "L138", "receiver": null}, {"caller_nid": "d_projects_depi_projects_grand_project_backend_nlp_sentencebuffer_preview", "callee": "join", "is_member_call": true, "source_file": "backend/nlp.py", "source_location": "L151", "receiver": null}, {"caller_nid": "d_projects_depi_projects_grand_project_backend_nlp_apply_token_corrections", "callee": "split", "is_member_call": true, "source_file": "backend/nlp.py", "source_location": "L179", "receiver": "text"}, {"caller_nid": "d_projects_depi_projects_grand_project_backend_nlp_apply_token_corrections", "callee": "join", "is_member_call": true, "source_file": "backend/nlp.py", "source_location": "L180", "receiver": null}, {"caller_nid": "d_projects_depi_projects_grand_project_backend_nlp_apply_token_corrections", "callee": "get", "is_member_call": true, "source_file": "backend/nlp.py", "source_location": "L180", "receiver": "TOKEN_CORRECTIONS"}, {"caller_nid": "d_projects_depi_projects_grand_project_backend_nlp_remove_consecutive_duplicates", "callee": "split", "is_member_call": true, "source_file": "backend/nlp.py", "source_location": "L184", "receiver": "text"}, {"caller_nid": "d_projects_depi_projects_grand_project_backend_nlp_remove_consecutive_duplicates", "callee": "append", "is_member_call": true, "source_file": "backend/nlp.py", "source_location": "L189", "receiver": "result"}, {"caller_nid": "d_projects_depi_projects_grand_project_backend_nlp_remove_consecutive_duplicates", "callee": "join", "is_member_call": true, "source_file": "backend/nlp.py", "source_location": "L191", "receiver": null}, {"caller_nid": "d_projects_depi_projects_grand_project_backend_nlp_normalise_whitespace", "callee": "strip", "is_member_call": true, "source_file": "backend/nlp.py", "source_location": "L195", "receiver": null}, {"caller_nid": "d_projects_depi_projects_grand_project_backend_nlp_normalise_whitespace", "callee": "sub", "is_member_call": true, "source_file": "backend/nlp.py", "source_location": "L195", "receiver": "re"}, {"caller_nid": "d_projects_depi_projects_grand_project_backend_nlp_arabert_correct", "callee": "debug", "is_member_call": true, "source_file": "backend/nlp.py", "source_location": "L217", "receiver": "logger"}, {"caller_nid": "d_projects_depi_projects_grand_project_backend_nlp_arabert_correct", "callee": "exc", "is_member_call": false, "indirect": true, "context": "argument", "source_file": "backend/nlp.py", "source_location": "L217"}]}